ud_co2s/__init__.py
ud_co2s/__main__.py
ud_co2s/_main.py
ud_co2s/cli.py
ud_co2s/py.typed
ud_co2s-1.0.0.dist-info/licenses/LICENSE
ud_co2s-1.0.0.dist-info/METADATA
ud_co2s-1.0.0.dist-info/WHEEL
ud_co2s-1.0.0.dist-info/entry_points.txt
ud_co2s-1.0.0.dist-info/top_level.txt
ud_co2s-1.0.0.dist-info/RECORD
