Metadata-Version: 2.4
Name: ud-co2s
Version: 1.0.0
Summary: Python package for reading sensor data from IODATA UD-CO2S or Pocket CO2 Sensor
Author-email: 34j <34j.95a2p@simplelogin.com>
License: MIT
Project-URL: Bug Tracker, https://github.com/34j/ud-co2s/issues
Project-URL: Changelog, https://github.com/34j/ud-co2s/blob/main/CHANGELOG.md
Project-URL: documentation, https://ud-co2s.readthedocs.io
Project-URL: repository, https://github.com/34j/ud-co2s
Classifier: Development Status :: 2 - Pre-Alpha
Classifier: Intended Audience :: Developers
Classifier: Natural Language :: English
Classifier: Operating System :: OS Independent
Classifier: Programming Language :: Python :: 3.9
Classifier: Programming Language :: Python :: 3.10
Classifier: Programming Language :: Python :: 3.11
Classifier: Programming Language :: Python :: 3.12
Classifier: Programming Language :: Python :: 3.13
Classifier: Topic :: Software Development :: Libraries
Requires-Python: >=3.11
License-File: LICENSE
Requires-Dist: aioserial>=1.3.1
Requires-Dist: attrs>=25.3.0
Requires-Dist: pandas>=2.3.2
Requires-Dist: plotext>=5.3.2
Requires-Dist: pyserial>=3.5
Requires-Dist: pystray>=0.19.5
Requires-Dist: rich>=10
Requires-Dist: seaborn>=0.13.2
Requires-Dist: thermofeel>=2.1.1
Requires-Dist: typer<1,>=0.15
Requires-Dist: unhandled-exit>=1.0.0
Dynamic: license-file
